<?xml version="1.0" encoding="UTF-8"?>
<!DOCTYPE mapper PUBLIC "-//mybatis.org//DTD Mapper 3.0//EN" "http://mybatis.org/dtd/mybatis-3-mapper.dtd">
<mapper namespace="rebue.afc.mapper.AfcTradeMapper">
  <resultMap id="BaseResultMap" type="rebue.afc.mo.AfcTradeMo">
    <!--
      WARNING - @mbg.generated
      This element is automatically generated by MyBatis Generator, do not modify.
    -->
    <id column="ID" jdbcType="BIGINT" property="id" />
    <result column="ACCOUNT_ID" jdbcType="BIGINT" property="accountId" />
    <result column="TRADE_TYPE" jdbcType="TINYINT" property="tradeType" />
    <result column="TRADE_AMOUNT" jdbcType="DECIMAL" property="tradeAmount" />
    <result column="CHANGE_AMOUNT1" jdbcType="DECIMAL" property="changeAmount1" />
    <result column="CHANGE_AMOUNT2" jdbcType="DECIMAL" property="changeAmount2" />
    <result column="TRADE_TITLE" jdbcType="VARCHAR" property="tradeTitle" />
    <result column="TRADE_DETAIL" jdbcType="VARCHAR" property="tradeDetail" />
    <result column="TRADE_TIME" jdbcType="TIMESTAMP" property="tradeTime" />
    <result column="ORDER_ID" jdbcType="VARCHAR" property="orderId" />
    <result column="ORDER_DETAIL_ID" jdbcType="VARCHAR" property="orderDetailId" />
    <result column="TRADE_VOUCHER_NO" jdbcType="VARCHAR" property="tradeVoucherNo" />
    <result column="OP_ID" jdbcType="BIGINT" property="opId" />
    <result column="MAC" jdbcType="VARCHAR" property="mac" />
    <result column="IP" jdbcType="VARCHAR" property="ip" />
  </resultMap>
  <sql id="Base_Column_List">
    <!--
      WARNING - @mbg.generated
      This element is automatically generated by MyBatis Generator, do not modify.
    -->
    ID, ACCOUNT_ID, TRADE_TYPE, TRADE_AMOUNT, CHANGE_AMOUNT1, CHANGE_AMOUNT2, TRADE_TITLE, 
    TRADE_DETAIL, TRADE_TIME, ORDER_ID, ORDER_DETAIL_ID, TRADE_VOUCHER_NO, OP_ID, MAC, 
    IP
  </sql>
  <select id="selectByPrimaryKey" parameterType="java.lang.Long" resultMap="BaseResultMap">
    <!--
      WARNING - @mbg.generated
      This element is automatically generated by MyBatis Generator, do not modify.
    -->
    select 
    <include refid="Base_Column_List" />
    from AFC_TRADE
    where ID = #{id,jdbcType=BIGINT}
  </select>
  <delete id="deleteByPrimaryKey" parameterType="java.lang.Long">
    <!--
      WARNING - @mbg.generated
      This element is automatically generated by MyBatis Generator, do not modify.
    -->
    delete from AFC_TRADE
    where ID = #{id,jdbcType=BIGINT}
  </delete>
  <insert id="insert" parameterType="rebue.afc.mo.AfcTradeMo">
    <!--
      WARNING - @mbg.generated
      This element is automatically generated by MyBatis Generator, do not modify.
    -->
    insert into AFC_TRADE (ID, ACCOUNT_ID, TRADE_TYPE, 
      TRADE_AMOUNT, CHANGE_AMOUNT1, CHANGE_AMOUNT2, 
      TRADE_TITLE, TRADE_DETAIL, TRADE_TIME, 
      ORDER_ID, ORDER_DETAIL_ID, TRADE_VOUCHER_NO, 
      OP_ID, MAC, IP)
    values (#{id,jdbcType=BIGINT}, #{accountId,jdbcType=BIGINT}, #{tradeType,jdbcType=TINYINT}, 
      #{tradeAmount,jdbcType=DECIMAL}, #{changeAmount1,jdbcType=DECIMAL}, #{changeAmount2,jdbcType=DECIMAL}, 
      #{tradeTitle,jdbcType=VARCHAR}, #{tradeDetail,jdbcType=VARCHAR}, #{tradeTime,jdbcType=TIMESTAMP}, 
      #{orderId,jdbcType=VARCHAR}, #{orderDetailId,jdbcType=VARCHAR}, #{tradeVoucherNo,jdbcType=VARCHAR}, 
      #{opId,jdbcType=BIGINT}, #{mac,jdbcType=VARCHAR}, #{ip,jdbcType=VARCHAR})
  </insert>
  <insert id="insertSelective" parameterType="rebue.afc.mo.AfcTradeMo">
    <!--
      WARNING - @mbg.generated
      This element is automatically generated by MyBatis Generator, do not modify.
    -->
    insert into AFC_TRADE
    <trim prefix="(" suffix=")" suffixOverrides=",">
      <if test="id != null">
        ID,
      </if>
      <if test="accountId != null">
        ACCOUNT_ID,
      </if>
      <if test="tradeType != null">
        TRADE_TYPE,
      </if>
      <if test="tradeAmount != null">
        TRADE_AMOUNT,
      </if>
      <if test="changeAmount1 != null">
        CHANGE_AMOUNT1,
      </if>
      <if test="changeAmount2 != null">
        CHANGE_AMOUNT2,
      </if>
      <if test="tradeTitle != null">
        TRADE_TITLE,
      </if>
      <if test="tradeDetail != null">
        TRADE_DETAIL,
      </if>
      <if test="tradeTime != null">
        TRADE_TIME,
      </if>
      <if test="orderId != null">
        ORDER_ID,
      </if>
      <if test="orderDetailId != null">
        ORDER_DETAIL_ID,
      </if>
      <if test="tradeVoucherNo != null">
        TRADE_VOUCHER_NO,
      </if>
      <if test="opId != null">
        OP_ID,
      </if>
      <if test="mac != null">
        MAC,
      </if>
      <if test="ip != null">
        IP,
      </if>
    </trim>
    <trim prefix="values (" suffix=")" suffixOverrides=",">
      <if test="id != null">
        #{id,jdbcType=BIGINT},
      </if>
      <if test="accountId != null">
        #{accountId,jdbcType=BIGINT},
      </if>
      <if test="tradeType != null">
        #{tradeType,jdbcType=TINYINT},
      </if>
      <if test="tradeAmount != null">
        #{tradeAmount,jdbcType=DECIMAL},
      </if>
      <if test="changeAmount1 != null">
        #{changeAmount1,jdbcType=DECIMAL},
      </if>
      <if test="changeAmount2 != null">
        #{changeAmount2,jdbcType=DECIMAL},
      </if>
      <if test="tradeTitle != null">
        #{tradeTitle,jdbcType=VARCHAR},
      </if>
      <if test="tradeDetail != null">
        #{tradeDetail,jdbcType=VARCHAR},
      </if>
      <if test="tradeTime != null">
        #{tradeTime,jdbcType=TIMESTAMP},
      </if>
      <if test="orderId != null">
        #{orderId,jdbcType=VARCHAR},
      </if>
      <if test="orderDetailId != null">
        #{orderDetailId,jdbcType=VARCHAR},
      </if>
      <if test="tradeVoucherNo != null">
        #{tradeVoucherNo,jdbcType=VARCHAR},
      </if>
      <if test="opId != null">
        #{opId,jdbcType=BIGINT},
      </if>
      <if test="mac != null">
        #{mac,jdbcType=VARCHAR},
      </if>
      <if test="ip != null">
        #{ip,jdbcType=VARCHAR},
      </if>
    </trim>
  </insert>
  <update id="updateByPrimaryKeySelective" parameterType="rebue.afc.mo.AfcTradeMo">
    <!--
      WARNING - @mbg.generated
      This element is automatically generated by MyBatis Generator, do not modify.
    -->
    update AFC_TRADE
    <set>
      <if test="accountId != null">
        ACCOUNT_ID = #{accountId,jdbcType=BIGINT},
      </if>
      <if test="tradeType != null">
        TRADE_TYPE = #{tradeType,jdbcType=TINYINT},
      </if>
      <if test="tradeAmount != null">
        TRADE_AMOUNT = #{tradeAmount,jdbcType=DECIMAL},
      </if>
      <if test="changeAmount1 != null">
        CHANGE_AMOUNT1 = #{changeAmount1,jdbcType=DECIMAL},
      </if>
      <if test="changeAmount2 != null">
        CHANGE_AMOUNT2 = #{changeAmount2,jdbcType=DECIMAL},
      </if>
      <if test="tradeTitle != null">
        TRADE_TITLE = #{tradeTitle,jdbcType=VARCHAR},
      </if>
      <if test="tradeDetail != null">
        TRADE_DETAIL = #{tradeDetail,jdbcType=VARCHAR},
      </if>
      <if test="tradeTime != null">
        TRADE_TIME = #{tradeTime,jdbcType=TIMESTAMP},
      </if>
      <if test="orderId != null">
        ORDER_ID = #{orderId,jdbcType=VARCHAR},
      </if>
      <if test="orderDetailId != null">
        ORDER_DETAIL_ID = #{orderDetailId,jdbcType=VARCHAR},
      </if>
      <if test="tradeVoucherNo != null">
        TRADE_VOUCHER_NO = #{tradeVoucherNo,jdbcType=VARCHAR},
      </if>
      <if test="opId != null">
        OP_ID = #{opId,jdbcType=BIGINT},
      </if>
      <if test="mac != null">
        MAC = #{mac,jdbcType=VARCHAR},
      </if>
      <if test="ip != null">
        IP = #{ip,jdbcType=VARCHAR},
      </if>
    </set>
    where ID = #{id,jdbcType=BIGINT}
  </update>
  <update id="updateByPrimaryKey" parameterType="rebue.afc.mo.AfcTradeMo">
    <!--
      WARNING - @mbg.generated
      This element is automatically generated by MyBatis Generator, do not modify.
    -->
    update AFC_TRADE
    set ACCOUNT_ID = #{accountId,jdbcType=BIGINT},
      TRADE_TYPE = #{tradeType,jdbcType=TINYINT},
      TRADE_AMOUNT = #{tradeAmount,jdbcType=DECIMAL},
      CHANGE_AMOUNT1 = #{changeAmount1,jdbcType=DECIMAL},
      CHANGE_AMOUNT2 = #{changeAmount2,jdbcType=DECIMAL},
      TRADE_TITLE = #{tradeTitle,jdbcType=VARCHAR},
      TRADE_DETAIL = #{tradeDetail,jdbcType=VARCHAR},
      TRADE_TIME = #{tradeTime,jdbcType=TIMESTAMP},
      ORDER_ID = #{orderId,jdbcType=VARCHAR},
      ORDER_DETAIL_ID = #{orderDetailId,jdbcType=VARCHAR},
      TRADE_VOUCHER_NO = #{tradeVoucherNo,jdbcType=VARCHAR},
      OP_ID = #{opId,jdbcType=BIGINT},
      MAC = #{mac,jdbcType=VARCHAR},
      IP = #{ip,jdbcType=VARCHAR}
    where ID = #{id,jdbcType=BIGINT}
  </update>
  <select id="selectAll" resultMap="BaseResultMap">
    <!--
      WARNING - @mbg.generated
      This element is automatically generated by MyBatis Generator, do not modify.
    -->
    select ID, ACCOUNT_ID, TRADE_TYPE, TRADE_AMOUNT, CHANGE_AMOUNT1, CHANGE_AMOUNT2, 
    TRADE_TITLE, TRADE_DETAIL, TRADE_TIME, ORDER_ID, ORDER_DETAIL_ID, TRADE_VOUCHER_NO, 
    OP_ID, MAC, IP
    from AFC_TRADE
  </select>
  <select id="selectSelective" parameterType="rebue.afc.mo.AfcTradeMo" resultMap="BaseResultMap">
    <!--
      WARNING - @mbg.generated
      This element is automatically generated by MyBatis Generator, do not modify.
    -->
    select 
    <include refid="Base_Column_List" />
    from AFC_TRADE
    <where>
      <if test="accountId != null">
        and ACCOUNT_ID = #{accountId,jdbcType=BIGINT}
      </if>
      <if test="tradeType != null">
        and TRADE_TYPE = #{tradeType,jdbcType=TINYINT}
      </if>
      <if test="tradeAmount != null">
        and TRADE_AMOUNT = #{tradeAmount,jdbcType=DECIMAL}
      </if>
      <if test="changeAmount1 != null">
        and CHANGE_AMOUNT1 = #{changeAmount1,jdbcType=DECIMAL}
      </if>
      <if test="changeAmount2 != null">
        and CHANGE_AMOUNT2 = #{changeAmount2,jdbcType=DECIMAL}
      </if>
      <if test="tradeTitle != null and tradeTitle != ''">
        and TRADE_TITLE = #{tradeTitle,jdbcType=VARCHAR}
      </if>
      <if test="tradeDetail != null and tradeDetail != ''">
        and TRADE_DETAIL = #{tradeDetail,jdbcType=VARCHAR}
      </if>
      <if test="tradeTime != null">
        and TRADE_TIME = #{tradeTime,jdbcType=TIMESTAMP}
      </if>
      <if test="orderId != null and orderId != ''">
        and ORDER_ID = #{orderId,jdbcType=VARCHAR}
      </if>
      <if test="orderDetailId != null and orderDetailId != ''">
        and ORDER_DETAIL_ID = #{orderDetailId,jdbcType=VARCHAR}
      </if>
      <if test="tradeVoucherNo != null and tradeVoucherNo != ''">
        and TRADE_VOUCHER_NO = #{tradeVoucherNo,jdbcType=VARCHAR}
      </if>
      <if test="opId != null">
        and OP_ID = #{opId,jdbcType=BIGINT}
      </if>
      <if test="mac != null and mac != ''">
        and MAC = #{mac,jdbcType=VARCHAR}
      </if>
      <if test="ip != null and ip != ''">
        and IP = #{ip,jdbcType=VARCHAR}
      </if>
    </where>
  </select>
  <select id="existByPrimaryKey" parameterType="java.lang.Long" resultType="boolean">
    <!--
      WARNING - @mbg.generated
      This element is automatically generated by MyBatis Generator, do not modify.
    -->
    select count(*) 
    from AFC_TRADE
    where ID = #{id,jdbcType=BIGINT}
  </select>
  <select id="existSelective" parameterType="rebue.afc.mo.AfcTradeMo" resultType="boolean">
    <!--
      WARNING - @mbg.generated
      This element is automatically generated by MyBatis Generator, do not modify.
    -->
    select count(*) 
    from AFC_TRADE
    <where>
      <if test="id != null and id != ''">
        and ID = #{id,jdbcType=BIGINT}
      </if>
      <if test="accountId != null and accountId != ''">
        and ACCOUNT_ID = #{accountId,jdbcType=BIGINT}
      </if>
      <if test="tradeType != null and tradeType != ''">
        and TRADE_TYPE = #{tradeType,jdbcType=TINYINT}
      </if>
      <if test="tradeAmount != null and tradeAmount != ''">
        and TRADE_AMOUNT = #{tradeAmount,jdbcType=DECIMAL}
      </if>
      <if test="changeAmount1 != null and changeAmount1 != ''">
        and CHANGE_AMOUNT1 = #{changeAmount1,jdbcType=DECIMAL}
      </if>
      <if test="changeAmount2 != null and changeAmount2 != ''">
        and CHANGE_AMOUNT2 = #{changeAmount2,jdbcType=DECIMAL}
      </if>
      <if test="tradeTitle != null and tradeTitle != ''">
        and TRADE_TITLE = #{tradeTitle,jdbcType=VARCHAR}
      </if>
      <if test="tradeDetail != null and tradeDetail != ''">
        and TRADE_DETAIL = #{tradeDetail,jdbcType=VARCHAR}
      </if>
      <if test="tradeTime != null and tradeTime != ''">
        and TRADE_TIME = #{tradeTime,jdbcType=TIMESTAMP}
      </if>
      <if test="orderId != null and orderId != ''">
        and ORDER_ID = #{orderId,jdbcType=VARCHAR}
      </if>
      <if test="orderDetailId != null and orderDetailId != ''">
        and ORDER_DETAIL_ID = #{orderDetailId,jdbcType=VARCHAR}
      </if>
      <if test="tradeVoucherNo != null and tradeVoucherNo != ''">
        and TRADE_VOUCHER_NO = #{tradeVoucherNo,jdbcType=VARCHAR}
      </if>
      <if test="opId != null and opId != ''">
        and OP_ID = #{opId,jdbcType=BIGINT}
      </if>
      <if test="mac != null and mac != ''">
        and MAC = #{mac,jdbcType=VARCHAR}
      </if>
      <if test="ip != null and ip != ''">
        and IP = #{ip,jdbcType=VARCHAR}
      </if>
    </where>
  </select>

	<select id="selectCashbackTrade" parameterType="rebue.afc.mo.AfcTradeMo" resultMap="BaseResultMap">
		<!-- 查询账号返现金交易信息 -->
		select ID, TRADE_TITLE, IFNULL(IFNULL(CHANGE_AMOUNT1, (TRADE_AMOUNT-CHANGE_AMOUNT1)), 0.00) AS TRADE_AMOUNT, TRADE_TIME
		from AFC_TRADE
		<where>
			and ACCOUNT_ID = #{accountId,jdbcType=BIGINT}
			and TRADE_TYPE in (11, 20, 51, 54, 60, 61)
		</where>
	</select>

	<!-- 查询账号余额交易信息 -->
	<select id="selectBalanceTrade" parameterType="rebue.afc.mo.AfcTradeMo" resultMap="BaseResultMap">
		select ID, TRADE_TITLE, IFNULL(TRADE_AMOUNT, 0.00) AS TRADE_AMOUNT, TRADE_TIME
		from AFC_TRADE
		<where>
			and ACCOUNT_ID = #{accountId,jdbcType=BIGINT}
			and TRADE_TYPE in (10, 20, 30, 31, 32, 50, 53, 60)
		</where>
	</select>
	
	<!-- 后台管理交易流水查询方法 -->
	<select id="selectTradeList" parameterType="rebue.afc.to.AfcTradeTo" resultType="rebue.afc.ro.AfcTradeListRo">
		select ACCOUNT_ID accountId, TRADE_AMOUNT tradeAmount, TRADE_TIME tradeTime,TRADE_TYPE tradeType,OP_ID opId
		from AFC_TRADE at , AFC_ACCOUNT aa
		<where>
	      <if test="accountIdStr != null and accountIdStr != ''">
	        and ACCOUNT_ID IN ${accountIdStr}
	      </if>
	      <if test="tradeTypeString != null and tradeTypeString != ''">
	        and TRADE_TYPE IN ${tradeTypeString}
	      </if>
	      <if test="tradeTimeStart != null  ">
			and TRADE_TIME &gt;= #{tradeTimeStart,jdbcType=TIMESTAMP}
		  </if>
		  <if test="tradeTimeEnd != null ">
			and TRADE_TIME &lt;= #{tradeTimeEnd,jdbcType=TIMESTAMP}
		  </if>
		   and at.ACCOUNT_ID = aa.ID and aa.ACCOUNT_TYPE = #{accountType,jdbcType=TINYINT}
       </where>
       ORDER BY TRADE_TIME DESC
	</select>
	
		<!-- 获取组织交易流水方法-->
	<select id="getTrade" parameterType="rebue.afc.to.GetAfcTradeTo" resultType="rebue.afc.mo.AfcTradeMo">
	    select 
	  	  <include refid="Base_Column_List" />
	    from AFC_TRADE 
		     where 	 ACCOUNT_ID = #{accountId,jdbcType=BIGINT}
		<where>
	      <if test="tradeTimeStart != null  ">
			and TRADE_TIME &gt;= #{tradeTimeStart,jdbcType=TIMESTAMP}
		  </if>
		  <if test="tradeTimeEnd != null ">
			and TRADE_TIME &lt;= #{tradeTimeEnd,jdbcType=TIMESTAMP}
		  </if>
       </where>
       ORDER BY TRADE_TIME DESC
	</select>
</mapper>